LICENSE
MANIFEST.in
setup.cfg
setup.py
./geoval/polygon/polygon_utils.c
doc/Makefile
doc/source/conf.py
doc/source/index.rst
doc/source/installation.rst
doc/source/introduction.rst
geoval/__init__.py
geoval/version.json
geoval.egg-info/PKG-INFO
geoval.egg-info/SOURCES.txt
geoval.egg-info/dependency_links.txt
geoval.egg-info/top_level.txt
geoval/core/__init__.py
geoval/core/data.py
geoval/core/mapping.py
geoval/core/netcdf.py
geoval/grid/__init__.py
geoval/grid/grid.py
geoval/polygon/__init__.py
geoval/polygon/polygon.py
geoval/polygon/polygon_utils.pyx
geoval/region/__init__.py
geoval/region/region_basic.py
geoval/statistic/__init__.py
geoval/statistic/lomb_scargle.py
geoval/statistic/mintrend.py
geoval/statistic/statistic_basic.py
tests/dump.pkl
tests/test_data.py
tests/test_grid.py
tests/test_mapping.py
tests/test_mintrend.py
tests/test_polygon.py
tests/test_read_coordinates.py
tests/test_region.py