Metadata-Version: 1.1
Name: geoval
Version: 0.1.5
Summary: geoval - python based geodata evaluation package
Home-page: https://github.com/pygeo/geoval
Author: Alexander Loew
Author-email: alexander.loew@lmu.de
License: APACHE 2
Keywords: data,science,climate,meteorology,model evaluation,benchmarking,metrics
Platform: UNKNOWN
Classifier: Intended Audience :: Science/Research
Classifier: Topic :: Scientific/Engineering :: Atmospheric Science
Classifier: Topic :: Scientific/Engineering :: GIS
Classifier: Topic :: Scientific/Engineering :: Visualization
Classifier: Programming Language :: Python :: 2.7
